<?xml version="1.0" encoding="utf-8"?>
<IfcProject Class="IfcProject" xmlns:xsi="http://www.w3.org/2001/XMLSchema-instance" GlobalId="3oUsrKbqD0wh41n0gL1Hqn" Name="0001" LongName="Project Name" Phase="Project Status">
	<OwnerHistory Class="IfcOwnerHistory" id="i1" CreationDate="1570561985">
		<OwningUser Class="IfcPersonAndOrganization">
			<ThePerson Class="IfcPerson" FamilyName="" GivenName="pipauwel" >
				<MiddleNames>
				  <MiddleName>Test</MiddleName>
				  <MiddleName>Me</MiddleName>
				</MiddleNames>
			</ThePerson>
			<TheOrganization Class="IfcOrganization" Name="This is the organisation" Description="" />
		</OwningUser>
		<OwningApplication Class="IfcApplication" Version="2019" ApplicationFullName="Autodesk Revit 2019 (ENU)" ApplicationIdentifier="Revit">
			<ApplicationDeveloper Class="IfcOrganization" Name="Autodesk Revit 2019 (ENU)" />
		</OwningApplication>
	</OwnerHistory>
	<IsDecomposedBy>
		<IfcRelAggregates GlobalId="3FNdo3HPD8IRkUvWf0t9M_">
			<RelatedObjects>
				<IfcObjectDefinition Class="IfcSite" GlobalId="3kIOd66qr36u4qFBFSUfRi" Name="Surface:295172" ObjectType="" CompositionType="ELEMENT" RefLatitude="181945" RefLongitude="263305" RefElevation="0">					
				</IfcObjectDefinition>
				<IfcObjectDefinition Class="IfcSite" GlobalId="3kIOd66qr36u4qFBFSUffO" Name="The Other Surface:295175" ObjectType="" CompositionType="ELEMENT" RefLatitude="181933" RefLongitude="263333" RefElevation="10">
					<IsDecomposedBy>
						<IfcRelAggregates GlobalId="0q7WH1A$f3GQXtVXZUIa3w">
							<OwnerHistory Class="IfcOwnerHistory" xsi:nil="true" href="i1" />
							<RelatedObjects>
								<IfcObjectDefinition Class="IfcBuilding" GlobalId="3oUsrKbqD0wh41n0gL1Hqm" Name="" LongName="" CompositionType="ELEMENT">
									<IsDecomposedBy>
										<IfcRelAggregates GlobalId="0bEVwXRmbBleAvzFSJirAn">
											<RelatedObjects>
												<IfcObjectDefinition Class="IfcBuildingStorey" GlobalId="3oUsrKbqD0wh41n0fg_kEY" Name="Level 1" LongName="Level 1" CompositionType="ELEMENT" Elevation="0" />
												<IfcObjectDefinition Class="IfcBuildingStorey" GlobalId="3oUsrKbqD0wh41n0fg_kZk" Name="Level 2" LongName="Level 2" CompositionType="ELEMENT" Elevation="4000" />
											</RelatedObjects>
										</IfcRelAggregates>
									</IsDecomposedBy>
									<BuildingAddress Class="IfcPostalAddress" Town="" Region="Boston" PostalCode="" Country="MA" />
								</IfcObjectDefinition>
							</RelatedObjects>
						</IfcRelAggregates>
					</IsDecomposedBy>
				</IfcObjectDefinition>
			</RelatedObjects>
		</IfcRelAggregates>
	</IsDecomposedBy>	
</IfcProject>